pace/bin/activate_this.py
pace/bin/rst2html.py
pace/bin/rst2html4.py
pace/bin/rst2html5.py
pace/bin/rst2latex.py
pace/bin/rst2man.py
pace/bin/rst2odt.py
pace/bin/rst2odt_prepstyles.py
pace/bin/rst2pseudoxml.py
pace/bin/rst2s5.py
pace/bin/rst2xetex.py
pace/bin/rst2xml.py
pace/bin/rstpep2html.py
pace/util/__init__.py
pace/util/_boundary_utils.py
pace/util/_capture_stream.py
pace/util/_corners.py
pace/util/_exceptions.py
pace/util/_legacy_restart.py
pace/util/_optional_imports.py
pace/util/_properties.py
pace/util/_timing.py
pace/util/_xarray.py
pace/util/boundary.py
pace/util/buffer.py
pace/util/caching_comm.py
pace/util/comm.py
pace/util/communicator.py
pace/util/constants.py
pace/util/cuda_kernels.py
pace/util/filesystem.py
pace/util/global_config.py
pace/util/halo_data_transformer.py
pace/util/halo_updater.py
pace/util/io.py
pace/util/local_comm.py
pace/util/mpi.py
pace/util/namelist.py
pace/util/nudging.py
pace/util/null_comm.py
pace/util/partitioner.py
pace/util/quantity.py
pace/util/rotate.py
pace/util/time.py
pace/util/types.py
pace/util/units.py
pace/util/utils.py
pace/util/zarr_monitor.py
pace/util/grid/__init__.py
pace/util/grid/eta.py
pace/util/grid/generation.py
pace/util/grid/geometry.py
pace/util/grid/global_setup.py
pace/util/grid/gnomonic.py
pace/util/grid/helper.py
pace/util/grid/mirror.py
pace/util/initialization/__init__.py
pace/util/initialization/allocator.py
pace/util/initialization/sizer.py
pace/util/testing/__init__.py
pace/util/testing/comparison.py
pace/util/testing/dummy_comm.py
pace/util/testing/gt4py_cupy.py
pace/util/testing/gt4py_numpy.py
pace_util-0.9.0.dist-info/LICENSE
pace_util-0.9.0.dist-info/METADATA
pace_util-0.9.0.dist-info/WHEEL
pace_util-0.9.0.dist-info/top_level.txt
pace_util-0.9.0.dist-info/RECORD
