Metadata-Version: 2.1
Name: pace-util
Version: 0.9.0
Summary: UNKNOWN
Home-page: https://github.com/ai2cm/pace
Author: Allen Institute of Artificial Intelligence
Author-email: jeremym@allenai.org
License: BSD license
Platform: UNKNOWN
Classifier: Development Status :: 2 - Pre-Alpha
Classifier: Intended Audience :: Developers
Classifier: License :: OSI Approved :: BSD License
Classifier: Natural Language :: English
Classifier: Programming Language :: Python :: 3
Classifier: Programming Language :: Python :: 3.8
Classifier: Programming Language :: Python :: 3.9
Requires-Python: >=3.8
License-File: LICENSE
Requires-Dist: cftime (>=1.2.1)
Requires-Dist: numpy (>=0.15.0)
Requires-Dist: fsspec (>=0.6.0)
Requires-Dist: typing-extensions (>=3.7.4)
Requires-Dist: f90nml (>=1.1.0)
Provides-Extra: netcdf
Requires-Dist: xarray (>=0.15.1) ; extra == 'netcdf'
Requires-Dist: scipy (>=1.3.1) ; extra == 'netcdf'
Provides-Extra: zarr
Requires-Dist: zarr (>=2.3.2) ; extra == 'zarr'
Requires-Dist: xarray (>=0.15.1) ; extra == 'zarr'
Requires-Dist: scipy (>=1.3.1) ; extra == 'zarr'
